odoo10_addon_shopinvader_category_image_for_product-10.0.1.0.0.99.dev3-py3.8-nspkg.pth
odoo/addons/shopinvader_category_image_for_product/README.rst
odoo/addons/shopinvader_category_image_for_product/__init__.py
odoo/addons/shopinvader_category_image_for_product/__manifest__.py
odoo/addons/shopinvader_category_image_for_product/data/ir_export.xml
odoo/addons/shopinvader_category_image_for_product/i18n/shopinvader_category_image_for_product.pot
odoo/addons/shopinvader_category_image_for_product/models/__init__.py
odoo/addons/shopinvader_category_image_for_product/models/shopinvader_variant.py
odoo/addons/shopinvader_category_image_for_product/readme/CONTRIBUTORS.rst
odoo/addons/shopinvader_category_image_for_product/readme/DESCRIPTION.rst
odoo/addons/shopinvader_category_image_for_product/static/description/index.html
odoo10_addon_shopinvader_category_image_for_product-10.0.1.0.0.99.dev3.dist-info/METADATA
odoo10_addon_shopinvader_category_image_for_product-10.0.1.0.0.99.dev3.dist-info/WHEEL
odoo10_addon_shopinvader_category_image_for_product-10.0.1.0.0.99.dev3.dist-info/namespace_packages.txt
odoo10_addon_shopinvader_category_image_for_product-10.0.1.0.0.99.dev3.dist-info/top_level.txt
odoo10_addon_shopinvader_category_image_for_product-10.0.1.0.0.99.dev3.dist-info/RECORD
